ingestor/__init__.py
rplus_ingestor_module-0.0.1.dist-info/WHEEL
rplus_ingestor_module-0.0.1.dist-info/METADATA
rplus_ingestor_module-0.0.1.dist-info/RECORD
